infonce/__init__.py
infonce/infonce.py
infonce-0.3.dist-info/LICENSE
infonce-0.3.dist-info/METADATA
infonce-0.3.dist-info/WHEEL
infonce-0.3.dist-info/top_level.txt
infonce-0.3.dist-info/RECORD
