Metadata-Version: 2.1
Name: infonce
Version: 0.3
Summary: Pytorch-based InfoNCE loss for self-supervised learning
Home-page: https://github.com/arashkhoeini/infonce
Author: Arash Khoeini
Author-email: arash.khoeini@gmail.com
License: UNKNOWN
Platform: UNKNOWN
Classifier: Programming Language :: Python :: 3
Classifier: License :: OSI Approved :: MIT License
Classifier: Operating System :: OS Independent
Requires-Python: >=3.6
Requires-Dist: torch>=2.0.0
